simpleSQLBuilder/QueryBuilder.py
simpleSQLBuilder/__init__.py
tests/__init__.py
tests/test_builder.py
simpleSQLBuilder-1.0.1.dist-info/METADATA
simpleSQLBuilder-1.0.1.dist-info/WHEEL
simpleSQLBuilder-1.0.1.dist-info/top_level.txt
simpleSQLBuilder-1.0.1.dist-info/RECORD
