Metadata-Version: 2.1
Name: simpleSQLBuilder
Version: 1.0.1
Summary: Building queries
Home-page: https://github.com/StAs0n41K/QueryBuilder
Author: Silkin S.A.
Author-email: stas.silkin.2016@gmail.com
License: UNKNOWN
Platform: any
Requires-Python: >=3.7
